breaker/.DS_Store
breaker/Home.md
breaker/__init__.py
breaker/__version__.py
breaker/_database.py
breaker/cl_utils.py
breaker/default_settings.yaml
breaker/update_ps1_atlas_footprint_tables.py
breaker/utKit.py
breaker/commonutils/__init__.py
breaker/commonutils/getpackagepath.py
breaker/fakers/__init__.py
breaker/fakers/generate_faker_catalogue.py
breaker/fakers/tests/test_generate_faker_catalogue.py
breaker/gracedb/__init__.py
breaker/gracedb/listen.py
breaker/gracedb/tests/__init__.py
breaker/gracedb/tests/test_listen.py
breaker/gracedb/tests/input/459770_bayestar.fits.gz
breaker/gracedb/tests/input/459770_lalinference.fits.gz
breaker/gracedb/tests/input/example-settings.yaml
breaker/plots/.DS_Store
breaker/plots/__init__.py
breaker/plots/longitude_coverage.py
breaker/plots/plot_multi_panel_alternate_map_comparison.py
breaker/plots/plot_wave_matched_source_maps.py
breaker/plots/plot_wave_observational_timelines.py
breaker/plots/tests/__init__.py
breaker/plots/tests/test_longitude_coverage.py
breaker/plots/tests/test_plot_multi_panel_alternate_map_comparison.py
breaker/plots/tests/test_plot_wave_observational_timelines.py
breaker/plots/tests/input/GW151226-LALInference_skymap_final.fits
breaker/plots/tests/input/GW151226-LALInference_skymap_initial.fits
breaker/plots/tests/input/GW151226-bayestar.fits
breaker/plots/tests/input/GW151226-skyprobcc_cWB.fits
breaker/plots/tests/output/GW151226-LALInference_skymap_final.fits
breaker/plots/tests/output/GW151226-LALInference_skymap_initial.fits
breaker/plots/tests/output/GW151226-bayestar.fits
breaker/plots/tests/output/GW151226-skyprobcc_cWB.fits
breaker/plots/tests/output/fits/G184098_GW151226-bayestar_breaker_skymap.fits
breaker/plots/tests/output/pdf/G184098_GW151226-bayestar_skymap_cartesian.pdf
breaker/plots/tests/output/pdf/G184098_GW151226-bayestar_skymap_gnomonic.pdf
breaker/plots/tests/output/pdf/G184098_GW151226-bayestar_skymap_mercator.pdf
breaker-2.0.1.dist-info/DESCRIPTION.rst
breaker-2.0.1.dist-info/METADATA
breaker-2.0.1.dist-info/RECORD
breaker-2.0.1.dist-info/WHEEL
breaker-2.0.1.dist-info/entry_points.txt
breaker-2.0.1.dist-info/metadata.json
breaker-2.0.1.dist-info/top_level.txt
