Metadata-Version: 2.0
Name: breaker
Version: 2.0.1
Summary: CL-tools for PanSTARRS & ATLAS LIGO-VIRGO (PSAT) group to aid surveys of the likely sky-locations of LIGO-VIRGO discovered Gravitational Waves
Home-page: https://github.com/thespacedoctor/breaker
Author: David Young
Author-email: davidrobertyoung@gmail.com
License: MIT
Download-URL: https://github.com/thespacedoctor/breaker/archive/v2.0.1.zip
Keywords: tools, panstarrs, atlas
Platform: UNKNOWN
Classifier: Development Status :: 4 - Beta
Classifier: License :: OSI Approved :: MIT License
Classifier: Programming Language :: Python :: 2.7
Classifier: Topic :: Utilities
Requires-Dist: HMpTy
Requires-Dist: astropy
Requires-Dist: crowdedText
Requires-Dist: docopt
Requires-Dist: fundamentals
Requires-Dist: healpy
Requires-Dist: ligo-gracedb
Requires-Dist: neddy
Requires-Dist: numpy
Requires-Dist: pymysql
Requires-Dist: pyyaml
Requires-Dist: qub-sherlock
Requires-Dist: requests
Requires-Dist: sphinx
Requires-Dist: sphinx-rtd-theme
